{
    "version": "5",
    "minVersion": "5",
    "assets": [
        "builtin/cube.mesh.bin",
        "builtin/meshphysical.mat.json",
        "assets/prefabs/room.prefab.json"
    ],
    "entities": [
        {
            "uuid": "0b7dadcb-ae32-4597-adc9-1239e4f7da24",
            "__class": "@egret/engine/GameEntity",
            "components": [
                {
                    "uuid": "43f5e419-ff7b-4a8c-8271-10e54962f6ac"
                },
                {
                    "uuid": "0105e9c8-d226-4bf8-83c5-ceac80d1bb07"
                }
            ]
        },
        {
            "uuid": "2f5d9aff-a014-42af-9931-055e4e2b4f6c",
            "__class": "@egret/engine/GameEntity",
            "components": [
                {
                    "uuid": "1583af9d-8fda-4564-88c8-73edeea56ab2"
                },
                {
                    "uuid": "ec0cec21-f890-4a27-af7a-873675c549d5"
                },
                {
                    "uuid": "7492c326-149b-47c6-925a-13019d166ff8"
                },
                {
                    "uuid": "aace32d6-63db-406e-821b-cb9cab45e116"
                }
            ]
        },
        {
            "uuid": "97d8213c-d178-4b87-b74d-ac1db417d2c4",
            "__class": "@egret/engine/GameEntity",
            "components": [
                {
                    "uuid": "38529515-9e8f-44b3-bbf9-ce9653bff1d1"
                },
                {
                    "uuid": "ae62ea19-98b1-42aa-a1c9-4f1e8f8864a7"
                },
                {
                    "uuid": "dba17bfd-dfec-4a30-9a9f-6697b0feb92e"
                },
                {
                    "uuid": "abd1c287-79c8-4f47-90a2-a8db400f80f6"
                },
                {
                    "uuid": "4d5a3d46-7958-4f34-a7e4-3cd130c33d08"
                },
                {
                    "uuid": "d88ff61c-de8d-42c0-9275-57cd3fdbf1a0"
                }
            ]
        },
        {
            "uuid": "1267aa30-32e5-43ba-b578-af6a0d36b7a3",
            "__class": "@egret/engine/GameEntity",
            "components": [
                {
                    "uuid": "31bc3ee1-a7f8-4aef-ae71-0691a77d24dc"
                },
                {
                    "uuid": "755ff4ff-b2be-4b8d-9f2e-22078c11f173"
                }
            ],
            "__extras": {
                "prefab": {
                    "__asset": 2
                }
            }
        },
        {
            "uuid": "f5642933-86dd-4f06-8a68-5860d2f51346",
            "__class": "@egret/engine/GameEntity",
            "components": [
                {
                    "uuid": "e04d3d87-9b18-482f-9014-7a6d96df851d"
                },
                {
                    "uuid": "7e945cc9-fe4d-4be8-a6ec-f27ee4681478"
                },
                {
                    "uuid": "00b06e4f-24cf-4a1e-8921-682210f6976c"
                },
                {
                    "uuid": "821f5179-9c36-4dfe-a2fc-083a6c2b6b76"
                }
            ],
            "__extras": {
                "linkedID": "4d79e69c-1112-45cd-8e7c-485d348349e7",
                "rootID": "1267aa30-32e5-43ba-b578-af6a0d36b7a3"
            }
        },
        {
            "uuid": "4c5741ed-1fc6-4c15-814f-2b8ee037e1fd",
            "__class": "@egret/engine/GameEntity",
            "components": [
                {
                    "uuid": "324aea1b-f277-461e-93a7-1f201000ae73"
                },
                {
                    "uuid": "81d9b71d-5839-49fa-a405-f9da45071a22"
                },
                {
                    "uuid": "c3ad720f-513b-4fb2-99ff-5adb42f226ed"
                },
                {
                    "uuid": "f1525218-244c-4b84-8380-9d62f2596efd"
                }
            ],
            "__extras": {
                "linkedID": "34d3f546-2816-4e2b-94d9-24034b316180",
                "rootID": "1267aa30-32e5-43ba-b578-af6a0d36b7a3"
            }
        },
        {
            "uuid": "bd79236a-5b40-439a-a91e-52d921e591f2",
            "__class": "@egret/engine/GameEntity",
            "components": [
                {
                    "uuid": "02eff086-7cdd-4258-8ea6-1a7fc72ada8a"
                },
                {
                    "uuid": "03e266a3-4b48-41a6-a45d-32932704d2bc"
                },
                {
                    "uuid": "5e6abf76-85db-4009-b1d5-ebbff1da8043"
                }
            ],
            "__extras": {
                "linkedID": "f8796b7e-b12c-4881-9a73-dbd15c830ed3",
                "rootID": "1267aa30-32e5-43ba-b578-af6a0d36b7a3"
            }
        }
    ],
    "components": [
        {
            "uuid": "43f5e419-ff7b-4a8c-8271-10e54962f6ac",
            "__class": "@egret/engine/TreeNode",
            "name": "Root",
            "children": [
                {
                    "uuid": "1583af9d-8fda-4564-88c8-73edeea56ab2"
                },
                {
                    "uuid": "38529515-9e8f-44b3-bbf9-ce9653bff1d1"
                },
                {
                    "uuid": "31bc3ee1-a7f8-4aef-ae71-0691a77d24dc"
                }
            ]
        },
        {
            "uuid": "1583af9d-8fda-4564-88c8-73edeea56ab2",
            "__class": "@egret/engine/TreeNode",
            "name": "Main Camera",
            "tag": "MainCamera"
        },
        {
            "uuid": "ec0cec21-f890-4a27-af7a-873675c549d5",
            "__class": "@egret/engine/Transform",
            "localPosition": [
                1.7937346239599552,
                4.691522325600847,
                -8.358863661549972
            ],
            "localRotation": [
                0.2688703238964081,
                0,
                0,
                0.9631763696670532
            ]
        },
        {
            "uuid": "7492c326-149b-47c6-925a-13019d166ff8",
            "__class": "@egret/render/Camera"
        },
        {
            "uuid": "aace32d6-63db-406e-821b-cb9cab45e116",
            "__class": "RotateAround",
            "lookAtPoint": [
                3,
                0,
                0
            ]
        },
        {
            "uuid": "38529515-9e8f-44b3-bbf9-ce9653bff1d1",
            "__class": "@egret/engine/TreeNode",
            "name": "WayPointCube"
        },
        {
            "uuid": "ae62ea19-98b1-42aa-a1c9-4f1e8f8864a7",
            "__class": "@egret/engine/Transform",
            "localPosition": [
                -1.5070411391872365,
                0.5,
                0
            ]
        },
        {
            "uuid": "dba17bfd-dfec-4a30-9a9f-6697b0feb92e",
            "__class": "@egret/render/MeshFilter",
            "mesh": {
                "__asset": 0
            }
        },
        {
            "uuid": "abd1c287-79c8-4f47-90a2-a8db400f80f6",
            "__class": "@egret/render/MeshRenderer",
            "_localBoundingBox": [
                -0.5,
                -0.5,
                -0.5,
                0.5,
                0.5,
                0.5
            ],
            "materials": [
                {
                    "__asset": 1
                }
            ]
        },
        {
            "uuid": "4d5a3d46-7958-4f34-a7e4-3cd130c33d08",
            "__class": "@egret/waypoint/WayPointsController",
            "systemSamplingPoints": [
                0,
                1.414195985605625,
                0,
                -0.004319697548191492,
                1.4131304054217542,
                -0.013744061476933698,
                -0.005123957160433485,
                1.4110324381795083,
                -0.03003903146524691,
                -0.0013752980036277227,
                1.4076163379877469,
                -0.04945538718134719,
                0.008270018101673595,
                1.4025382103440343,
                -0.07252390215576857,
                0.025256910853675565,
                1.395460562620638,
                -0.09954382102840201,
                0.05053050674959309,
                1.3862280512992093,
                -0.13015884500136718,
                0.08368563089293322,
                1.3750791248373435,
                -0.16306402045753615,
                0.12291417796869586,
                1.3625980885038365,
                -0.19648672219139413,
                0.1660657704430509,
                1.3493890398474997,
                -0.22906452745040368,
                0.21152121815930203,
                1.3358609068238663,
                -0.26013551605279295,
                0.25827775330518826,
                1.3222403232137898,
                -0.28949602040998823,
                0.3058417407062127,
                1.3086174434256124,
                -0.31720117539518444,
                0.35388495835067896,
                1.2950471757850774,
                -0.3433259808801444,
                0.4022933817179992,
                1.2815330911786054,
                -0.3680007786240875,
                0.45100295434478344,
                1.2680720864111048,
                -0.3913285673243842,
                0.4999795521790263,
                1.2546578943385982,
                -0.4133882935548579,
                0.5492409106130139,
                1.2412738441381068,
                -0.43425195325484,
                0.5988155526608832,
                1.2279033323137634,
                -0.4539699976941386,
                0.6487202277650002,
                1.2145351804140616,
                -0.4725671610083172,
                0.69900827006412,
                1.2011501899734236,
                -0.4900634611920354,
                0.7497215790131473,
                1.1877337588013337,
                -0.506456700970339,
                0.8009173305177495,
                1.1742685359591545,
                -0.5217324434906696,
                0.8526563292884032,
                1.1607374111343802,
                -0.5358591002984312,
                0.9050072669137592,
                1.147122333920834,
                -0.5487876528523818,
                0.958049267688841,
                1.1334036652194526,
                -0.5604494343482377,
                1.0118716643178645,
                1.11956031122458,
                -0.5707518729607626,
                1.0665615754579134,
                1.1055730212871977,
                -0.5795710299990502,
                1.122260141802851,
                1.0914102341880012,
                -0.5867523546193583,
                1.1790713426114852,
                1.0770516720631793,
                -0.5920857832755091,
                1.2371364289764326,
                1.0624697490049688,
                -0.5953024377074838,
                1.296601157335992,
                1.047638526482465,
                -0.5960490810114355,
                1.3575890896022789,
                1.0325411202919035,
                -0.5938608725632721,
                1.4202068958158014,
                1.0171693723965956,
                -0.5881250362245737,
                1.4843329777760528,
                1.0015766213855732,
                -0.5780635396169098,
                1.5495643632027367,
                0.9858900555603611,
                -0.5627429615900557,
                1.6147752765159873,
                0.9704136140938742,
                -0.5412621241797774,
                1.677860248603975,
                0.9556768565005382,
                -0.5132031820317524,
                1.7360723527582431,
                0.9423345813599225,
                -0.47917325180795,
                1.7871375017291151,
                0.9308919374850759,
                -0.44083072376227095,
                1.830258289437876,
                0.9214823339928473,
                -0.4001013423373372,
                1.8659812850623374,
                0.9139249811946164,
                -0.35839538448780983,
                1.895341776318725,
                0.9079363189210812,
                -0.3165884715900991,
                1.9194613568733194,
                0.9032271811829258,
                -0.2750705645311083,
                1.9392505563298856,
                0.8995655084574193,
                -0.2340835096443607,
                1.9554772163657628,
                0.8967605369198732,
                -0.19367509554753562,
                1.968719763286751,
                0.8946681766666013,
                -0.15389973527076944,
                1.9794713424614667,
                0.8931701692223152,
                -0.11465132571528158,
                1.988078312174719,
                0.8921803129115498,
                -0.0759649878307274,
                1.9948453548595975,
                0.8916264564289234,
                -0.037747236454475114,
                2,
                0.8914526697173812,
                0,
                2,
                0.8914526697173812,
                0,
                2.024169777234228,
                0.8923020732635952,
                0.04617177351239113,
                2.04958246682476,
                0.894874860100101,
                0.09040379129551751,
                2.0762697445699194,
                0.8992067652732172,
                0.13262364059304002,
                2.1042650201883033,
                0.9053321802903471,
                0.1727605798094816,
                2.1336129541011504,
                0.9132870705080377,
                0.21075638915603206,
                2.164325765926314,
                0.9230962328814833,
                0.246510539109028,
                2.1964557861669607,
                0.9347934532302506,
                0.27997204952210325,
                2.230010224173678,
                0.9483935429603135,
                0.31104160703299183,
                2.2650215007497843,
                0.9639154610765277,
                0.3396508332597278,
                2.301513440033508,
                0.98137009443421,
                0.3657259433139891,
                2.33949180581323,
                1.000753402906411,
                0.3891867319602314,
                2.378964113621411,
                1.022054463346087,
                0.40996406530408863,
                2.419927932740591,
                1.045248905403494,
                0.4279935730682017,
                2.462369056711021,
                1.0702964813684135,
                0.4432183527387756,
                2.506259659306779,
                1.0971386384416209,
                0.45559198322777633,
                2.551560323287701,
                1.1256986451619468,
                0.465082440012293,
                2.598216072118965,
                1.1558782996883097,
                0.4716739548523528,
                2.6461397640231605,
                1.187546135289697,
                0.4753693607500362,
                2.6952415157388336,
                1.2205561390225674,
                0.4761971135694357,
                2.745398203300317,
                1.2547277763602362,
                0.47421118957692,
                2.796472878152547,
                1.2898593946975172,
                0.46949468811077477,
                2.8483007569170677,
                1.325719834490397,
                0.462162024029975,
                2.9007103268225816,
                1.36206471716997,
                0.4523571667475999,
                2.953502518886974,
                1.3986243885351268,
                0.44025617377402043,
                3.006475826188718,
                1.4351241630444194,
                0.42606126746991824,
                3.059421093883418,
                1.4712838815693696,
                0.40999852238922685,
                3.1121295369194923,
                1.5068267359046543,
                0.39231209275406287,
                3.1644002185976055,
                1.5414874954841133,
                0.3732572451835818,
                3.216035442291525,
                1.575012399018328,
                0.3530974094883514,
                3.26686551521722,
                1.6071777055958323,
                0.33208989604284267,
                3.3167269549898104,
                1.637777195405203,
                0.31048970387917774,
                3.3654861055321077,
                1.6666381490270088,
                0.28853582438072334,
                3.4130211939722974,
                1.6936106390613093,
                0.26645551379130716,
                3.459245424732676,
                1.7185805266338834,
                0.244451065670236,
                3.5040750517817116,
                1.7414507058573918,
                0.2227127586727171,
                3.5474564209342034,
                1.7621548359339263,
                0.20140486072369643,
                3.5893533322160724,
                1.7806484070073862,
                0.18067084072272502,
                3.6297404895432965,
                1.7969041144091373,
                0.16063649584550624,
                3.668606100174831,
                1.8109114760169187,
                0.14140890970000258,
                3.7059500070326994,
                1.8226741148785988,
                0.12307787232502937,
                3.741781843149298,
                1.8322071342378572,
                0.10571751512846278,
                3.7761091410226104,
                1.8395327856173633,
                0.08939281508783874,
                3.8089583546749184,
                1.844684089365297,
                0.0741503424534674,
                3.840362994230496,
                1.847698694389248,
                0.060025263328579305,
                3.870332120101992,
                1.8486164876282807,
                0.04705599172630723,
                3.898919327812145,
                1.8474827895185901,
                0.035254623533377515,
                3.9261388508423356,
                1.8443448635554833,
                0.024643985301446455,
                3.9520359698514387,
                1.839250158778352,
                0.01522881190933445,
                3.976645420941094,
                1.8322468093200803,
                0.007013747076877838,
                4,
                1.82338398030633,
                0,
                4,
                1.82338398030633,
                0,
                4.028762529548779,
                1.800939769645723,
                -0.03466415652886369,
                4.062015991505361,
                1.7763664141661932,
                -0.06330876747272696,
                4.098788324040903,
                1.750369583802122,
                -0.08567689393119901,
                4.1380553330788885,
                1.723611521722323,
                -0.10207706547653296,
                4.178979435116932,
                1.6965816376820366,
                -0.11316194412398459,
                4.220932816829017,
                1.6696129124840282,
                -0.11967755895089889,
                4.263499429763097,
                1.6428995772606425,
                -0.12233415594145007,
                4.306418780669257,
                1.616543470763127,
                -0.12174483501954513,
                4.349539066072392,
                1.5905876240958376,
                -0.11841441759598141,
                4.392728498667643,
                1.5650704935813264,
                -0.11275701139007781,
                4.435946460047602,
                1.539983018981139,
                -0.10510402380153022,
                4.479154559542897,
                1.515321210143838,
                -0.09572604308933967,
                4.522332857674198,
                1.4910753976437823,
                -0.08484417232202826,
                4.565474710040818,
                1.4672326053579312,
                -0.07263989781262292,
                4.608581487126931,
                1.4437790190289639,
                -0.05926338995183776,
                4.651644206789801,
                1.4207093716509354,
                -0.044845271264352206,
                4.694683036270074,
                1.3980053128732537,
                -0.029488040619204785,
                4.737707817828234,
                1.375656544480713,
                -0.013281981676343119,
                4.780715864599814,
                1.35366122059253,
                0.003689936377427476,
                4.823733885732144,
                1.3320042920122885,
                0.021366369483976508,
                4.8667594601502335,
                1.3106872867167783,
                0.03968274232985684,
                4.90981513204255,
                1.2897008844525983,
                0.05859181867775351,
                4.952908914439559,
                1.2690446253184846,
                0.07804609364574643,
                4.996052790496983,
                1.2487176453405446,
                0.09800458344747102,
                5.039263617617541,
                1.2287184186689721,
                0.11843267821685165,
                5.082551188316145,
                1.2090503613240804,
                0.13929586168401192,
                5.125931268874762,
                1.1897158251265192,
                0.1605652418193302,
                5.169418110051545,
                1.1707196737488992,
                0.18221351075421865,
                5.213026544119612,
                1.1520684363770233,
                0.20421547107187332,
                5.2567722875240595,
                1.1337703482407773,
                0.22654777143461813,
                5.300669567291459,
                1.1158365259416876,
                0.24918728682965025,
                5.344739239377444,
                1.098277914190782,
                0.27211492673323256,
                5.388996293731996,
                1.081110676965015,
                0.2953087959909562,
                5.4334570523187935,
                1.0643535368835428,
                0.3187474807790613,
                5.4781506783224,
                1.04802409806061,
                0.34241575384628,
                5.523084420900094,
                1.032152173020642,
                0.36628571843482294,
                5.568298000813408,
                1.0167608481485169,
                0.39034509969535663,
                5.613795610788045,
                1.0018911339761594,
                0.41456051629376944,
                5.659623955651753,
                0.9875766018647756,
                0.4389182460663613,
                5.705793568719449,
                0.9738704793655272,
                0.46338148097407117,
                5.752332776237838,
                0.9608296071008549,
                0.4879179737125386,
                5.799281406343578,
                0.9485193866704182,
                0.5124952042689102,
                5.846663754931033,
                0.937023703750671,
                0.5370644036699317,
                5.8945028456535535,
                0.9264436481063367,
                0.5615659765614429,
                5.942819990390578,
                0.916901670000005,
                0.5859264705180915,
                5.99164521342755,
                0.9085454009677731,
                0.6100599253280999,
                6.040958469841793,
                0.9015642241021067,
                0.6338341003834275,
                6.090728586459097,
                0.8961882901417116,
                0.6570847531743789,
                6.140867868344389,
                0.8927024195001962,
                0.6795875005979988,
                6.191216357974574,
                0.8914526697173812,
                0.7010448476742404
            ],
            "curvePath": [
                0,
                1.414195985605625,
                0,
                -0.12078683303616333,
                1.4012127096512152,
                -0.2625342053166959,
                1.858906772690745,
                0.8914526697173812,
                -1.1988911314897788,
                2,
                0.8914526697173812,
                0,
                2,
                0.8914526697173812,
                0,
                2.5,
                0.8914526697173812,
                1,
                3.5175647275385296,
                2.0308026294327877,
                0.13607868756203167,
                4,
                1.82338398030633,
                0,
                4,
                1.82338398030633,
                0,
                4.3090458274074654,
                1.5742776979807611,
                -0.4404071245417053,
                5.529985287454975,
                0.8914526697173812,
                0.4278468406330015,
                6.191216357974574,
                0.8914526697173812,
                0.7010448476742404
            ],
            "pointPercent": [
                0,
                0.006666666666666667,
                0.013333333333333334,
                0.02,
                0.02666666666666667,
                0.03333333333333333,
                0.04,
                0.04666666666666667,
                0.05333333333333334,
                0.06,
                0.06666666666666667,
                0.07333333333333333,
                0.08,
                0.08666666666666667,
                0.09333333333333334,
                0.1,
                0.10666666666666667,
                0.11333333333333333,
                0.12,
                0.12666666666666668,
                0.13333333333333333,
                0.14,
                0.14666666666666667,
                0.15333333333333332,
                0.16,
                0.16666666666666666,
                0.17333333333333334,
                0.18,
                0.18666666666666668,
                0.19333333333333333,
                0.2,
                0.20666666666666667,
                0.21333333333333335,
                0.22,
                0.22666666666666666,
                0.23333333333333334,
                0.24,
                0.24666666666666667,
                0.25333333333333335,
                0.26,
                0.26666666666666666,
                0.2733333333333333,
                0.28,
                0.2866666666666667,
                0.29333333333333333,
                0.3,
                0.30666666666666664,
                0.31333333333333335,
                0.32,
                0.32666666666666666,
                0.3333333333333333,
                0.34,
                0.3466666666666667,
                0.35333333333333333,
                0.36,
                0.36666666666666664,
                0.37333333333333335,
                0.38,
                0.38666666666666666,
                0.3933333333333333,
                0.4,
                0.4066666666666667,
                0.41333333333333333,
                0.42,
                0.4266666666666667,
                0.43333333333333335,
                0.44,
                0.44666666666666666,
                0.4533333333333333,
                0.46,
                0.4666666666666667,
                0.47333333333333333,
                0.48,
                0.4866666666666667,
                0.49333333333333335,
                0.5,
                0.5066666666666667,
                0.5133333333333333,
                0.52,
                0.5266666666666666,
                0.5333333333333333,
                0.54,
                0.5466666666666666,
                0.5533333333333333,
                0.56,
                0.5666666666666667,
                0.5733333333333334,
                0.58,
                0.5866666666666667,
                0.5933333333333334,
                0.6,
                0.6066666666666667,
                0.6133333333333333,
                0.62,
                0.6266666666666667,
                0.6333333333333333,
                0.64,
                0.6466666666666666,
                0.6533333333333333,
                0.66,
                0.6666666666666666,
                0.6733333333333333,
                0.68,
                0.6866666666666666,
                0.6933333333333334,
                0.7,
                0.7066666666666667,
                0.7133333333333334,
                0.72,
                0.7266666666666667,
                0.7333333333333333,
                0.74,
                0.7466666666666667,
                0.7533333333333333,
                0.76,
                0.7666666666666667,
                0.7733333333333333,
                0.78,
                0.7866666666666666,
                0.7933333333333333,
                0.8,
                0.8066666666666666,
                0.8133333333333334,
                0.82,
                0.8266666666666667,
                0.8333333333333334,
                0.84,
                0.8466666666666667,
                0.8533333333333334,
                0.86,
                0.8666666666666667,
                0.8733333333333333,
                0.88,
                0.8866666666666667,
                0.8933333333333333,
                0.9,
                0.9066666666666666,
                0.9133333333333333,
                0.92,
                0.9266666666666666,
                0.9333333333333333,
                0.94,
                0.9466666666666667,
                0.9533333333333334,
                0.96,
                0.9666666666666667,
                0.9733333333333334,
                0.98,
                0.9866666666666667,
                0.9933333333333333,
                1,
                1.0066666666666666,
                1.0133333333333334,
                0,
                0.006666666666666667,
                0.013333333333333334,
                0.02,
                0.02666666666666667,
                0.03333333333333333,
                0.04,
                0.04666666666666667,
                0.05333333333333334,
                0.06,
                0.06666666666666667,
                0.07333333333333333,
                0.08,
                0.08666666666666667,
                0.09333333333333334,
                0.1,
                0.10666666666666667,
                0.11333333333333333,
                0.12,
                0.12666666666666668,
                0.13333333333333333,
                0.14,
                0.14666666666666667,
                0.15333333333333332,
                0.16,
                0.16666666666666666,
                0.17333333333333334,
                0.18,
                0.18666666666666668,
                0.19333333333333333,
                0.2,
                0.20666666666666667,
                0.21333333333333335,
                0.22,
                0.22666666666666666,
                0.23333333333333334,
                0.24,
                0.24666666666666667,
                0.25333333333333335,
                0.26,
                0.26666666666666666,
                0.2733333333333333,
                0.28,
                0.2866666666666667,
                0.29333333333333333,
                0.3,
                0.30666666666666664,
                0.31333333333333335,
                0.32,
                0.32666666666666666,
                0.3333333333333333,
                0.34,
                0.3466666666666667,
                0.35333333333333333,
                0.36,
                0.36666666666666664,
                0.37333333333333335,
                0.38,
                0.38666666666666666,
                0.3933333333333333,
                0.4,
                0.4066666666666667,
                0.41333333333333333,
                0.42,
                0.4266666666666667,
                0.43333333333333335,
                0.44,
                0.44666666666666666,
                0.4533333333333333,
                0.46,
                0.4666666666666667,
                0.47333333333333333,
                0.48,
                0.4866666666666667,
                0.49333333333333335,
                0.5,
                0.5066666666666667,
                0.5133333333333333,
                0.52,
                0.5266666666666666,
                0.5333333333333333,
                0.54,
                0.5466666666666666,
                0.5533333333333333,
                0.56,
                0.5666666666666667,
                0.5733333333333334,
                0.58,
                0.5866666666666667,
                0.5933333333333334,
                0.6,
                0.6066666666666667,
                0.6133333333333333,
                0.62,
                0.6266666666666667,
                0.6333333333333333,
                0.64,
                0.6466666666666666,
                0.6533333333333333,
                0.66,
                0.6666666666666666,
                0.6733333333333333,
                0.68,
                0.6866666666666666,
                0.6933333333333334,
                0.7,
                0.7066666666666667,
                0.7133333333333334,
                0.72,
                0.7266666666666667,
                0.7333333333333333,
                0.74,
                0.7466666666666667,
                0.7533333333333333,
                0.76,
                0.7666666666666667,
                0.7733333333333333,
                0.78,
                0.7866666666666666,
                0.7933333333333333,
                0.8,
                0.8066666666666666,
                0.8133333333333334,
                0.82,
                0.8266666666666667,
                0.8333333333333334,
                0.84,
                0.8466666666666667,
                0.8533333333333334,
                0.86,
                0.8666666666666667,
                0.8733333333333333,
                0.88,
                0.8866666666666667,
                0.8933333333333333,
                0.9,
                0.9066666666666666,
                0.9133333333333333,
                0.92,
                0.9266666666666666,
                0.9333333333333333,
                0.94,
                0.9466666666666667,
                0.9533333333333334,
                0.96,
                0.9666666666666667,
                0.9733333333333334,
                0.98,
                0.9866666666666667,
                0.9933333333333333,
                1,
                1.0066666666666666,
                1.0133333333333334,
                0,
                0.006666666666666667,
                0.013333333333333334,
                0.02,
                0.02666666666666667,
                0.03333333333333333,
                0.04,
                0.04666666666666667,
                0.05333333333333334,
                0.06,
                0.06666666666666667,
                0.07333333333333333,
                0.08,
                0.08666666666666667,
                0.09333333333333334,
                0.1,
                0.10666666666666667,
                0.11333333333333333,
                0.12,
                0.12666666666666668,
                0.13333333333333333,
                0.14,
                0.14666666666666667,
                0.15333333333333332,
                0.16,
                0.16666666666666666,
                0.17333333333333334,
                0.18,
                0.18666666666666668,
                0.19333333333333333,
                0.2,
                0.20666666666666667,
                0.21333333333333335,
                0.22,
                0.22666666666666666,
                0.23333333333333334,
                0.24,
                0.24666666666666667,
                0.25333333333333335,
                0.26,
                0.26666666666666666,
                0.2733333333333333,
                0.28,
                0.2866666666666667,
                0.29333333333333333,
                0.3,
                0.30666666666666664,
                0.31333333333333335,
                0.32,
                0.32666666666666666,
                0.3333333333333333,
                0.34,
                0.3466666666666667,
                0.35333333333333333,
                0.36,
                0.36666666666666664,
                0.37333333333333335,
                0.38,
                0.38666666666666666,
                0.3933333333333333,
                0.4,
                0.4066666666666667,
                0.41333333333333333,
                0.42,
                0.4266666666666667,
                0.43333333333333335,
                0.44,
                0.44666666666666666,
                0.4533333333333333,
                0.46,
                0.4666666666666667,
                0.47333333333333333,
                0.48,
                0.4866666666666667,
                0.49333333333333335,
                0.5,
                0.5066666666666667,
                0.5133333333333333,
                0.52,
                0.5266666666666666,
                0.5333333333333333,
                0.54,
                0.5466666666666666,
                0.5533333333333333,
                0.56,
                0.5666666666666667,
                0.5733333333333334,
                0.58,
                0.5866666666666667,
                0.5933333333333334,
                0.6,
                0.6066666666666667,
                0.6133333333333333,
                0.62,
                0.6266666666666667,
                0.6333333333333333,
                0.64,
                0.6466666666666666,
                0.6533333333333333,
                0.66,
                0.6666666666666666,
                0.6733333333333333,
                0.68,
                0.6866666666666666,
                0.6933333333333334,
                0.7,
                0.7066666666666667,
                0.7133333333333334,
                0.72,
                0.7266666666666667,
                0.7333333333333333,
                0.74,
                0.7466666666666667,
                0.7533333333333333,
                0.76,
                0.7666666666666667,
                0.7733333333333333,
                0.78,
                0.7866666666666666,
                0.7933333333333333,
                0.8,
                0.8066666666666666,
                0.8133333333333334,
                0.82,
                0.8266666666666667,
                0.8333333333333334,
                0.84,
                0.8466666666666667,
                0.8533333333333334,
                0.86,
                0.8666666666666667,
                0.8733333333333333,
                0.88,
                0.8866666666666667,
                0.8933333333333333,
                0.9,
                0.9066666666666666,
                0.9133333333333333,
                0.92,
                0.9266666666666666,
                0.9333333333333333,
                0.94,
                0.9466666666666667,
                0.9533333333333334,
                0.96,
                0.9666666666666667,
                0.9733333333333334,
                0.98,
                0.9866666666666667,
                0.9933333333333333,
                1,
                1.0066666666666666,
                1.0133333333333334,
                0,
                0.006666666666666667,
                0.013333333333333334,
                0.02,
                0.02666666666666667,
                0.03333333333333333,
                0.04,
                0.04666666666666667,
                0.05333333333333334,
                0.06,
                0.06666666666666667,
                0.07333333333333333,
                0.08,
                0.08666666666666667,
                0.09333333333333334,
                0.1,
                0.10666666666666667,
                0.11333333333333333,
                0.12,
                0.12666666666666668,
                0.13333333333333333,
                0.14,
                0.14666666666666667,
                0.15333333333333332,
                0.16,
                0.16666666666666666,
                0.17333333333333334,
                0.18,
                0.18666666666666668,
                0.19333333333333333,
                0.2,
                0.20666666666666667,
                0.21333333333333335,
                0.22,
                0.22666666666666666,
                0.23333333333333334,
                0.24,
                0.24666666666666667,
                0.25333333333333335,
                0.26,
                0.26666666666666666,
                0.2733333333333333,
                0.28,
                0.2866666666666667,
                0.29333333333333333,
                0.3,
                0.30666666666666664,
                0.31333333333333335,
                0.32,
                0.32666666666666666,
                0.3333333333333333,
                0.34,
                0.3466666666666667,
                0.35333333333333333,
                0.36,
                0.36666666666666664,
                0.37333333333333335,
                0.38,
                0.38666666666666666,
                0.3933333333333333,
                0.4,
                0.4066666666666667,
                0.41333333333333333,
                0.42,
                0.4266666666666667,
                0.43333333333333335,
                0.44,
                0.44666666666666666,
                0.4533333333333333,
                0.46,
                0.4666666666666667,
                0.47333333333333333,
                0.48,
                0.4866666666666667,
                0.49333333333333335,
                0.5,
                0.5066666666666667,
                0.5133333333333333,
                0.52,
                0.5266666666666666,
                0.5333333333333333,
                0.54,
                0.5466666666666666,
                0.5533333333333333,
                0.56,
                0.5666666666666667,
                0.5733333333333334,
                0.58,
                0.5866666666666667,
                0.5933333333333334,
                0.6,
                0.6066666666666667,
                0.6133333333333333,
                0.62,
                0.6266666666666667,
                0.6333333333333333,
                0.64,
                0.6466666666666666,
                0.6533333333333333,
                0.66,
                0.6666666666666666,
                0.6733333333333333,
                0.68,
                0.6866666666666666,
                0.6933333333333334,
                0.7,
                0.7066666666666667,
                0.7133333333333334,
                0.72,
                0.7266666666666667,
                0.7333333333333333,
                0.74,
                0.7466666666666667,
                0.7533333333333333,
                0.76,
                0.7666666666666667,
                0.7733333333333333,
                0.78,
                0.7866666666666666,
                0.7933333333333333,
                0.8,
                0.8066666666666666,
                0.8133333333333334,
                0.82,
                0.8266666666666667,
                0.8333333333333334,
                0.84,
                0.8466666666666667,
                0.8533333333333334,
                0.86,
                0.8666666666666667,
                0.8733333333333333,
                0.88,
                0.8866666666666667,
                0.8933333333333333,
                0.9,
                0.9066666666666666,
                0.9133333333333333,
                0.92,
                0.9266666666666666,
                0.9333333333333333,
                0.94,
                0.9466666666666667,
                0.9533333333333334,
                0.96,
                0.9666666666666667,
                0.9733333333333334,
                0.98,
                0.9866666666666667,
                0.9933333333333333,
                1,
                1.0066666666666666,
                1.0133333333333334,
                0,
                0.006666666666666667,
                0.013333333333333334,
                0.02,
                0.02666666666666667,
                0.03333333333333333,
                0.04,
                0.04666666666666667,
                0.05333333333333334,
                0.06,
                0.06666666666666667,
                0.07333333333333333,
                0.08,
                0.08666666666666667,
                0.09333333333333334,
                0.1,
                0.10666666666666667,
                0.11333333333333333,
                0.12,
                0.12666666666666668,
                0.13333333333333333,
                0.14,
                0.14666666666666667,
                0.15333333333333332,
                0.16,
                0.16666666666666666,
                0.17333333333333334,
                0.18,
                0.18666666666666668,
                0.19333333333333333,
                0.2,
                0.20666666666666667,
                0.21333333333333335,
                0.22,
                0.22666666666666666,
                0.23333333333333334,
                0.24,
                0.24666666666666667,
                0.25333333333333335,
                0.26,
                0.26666666666666666,
                0.2733333333333333,
                0.28,
                0.2866666666666667,
                0.29333333333333333,
                0.3,
                0.30666666666666664,
                0.31333333333333335,
                0.32,
                0.32666666666666666,
                0.3333333333333333,
                0.34,
                0.3466666666666667,
                0.35333333333333333,
                0.36,
                0.36666666666666664,
                0.37333333333333335,
                0.38,
                0.38666666666666666,
                0.3933333333333333,
                0.4,
                0.4066666666666667,
                0.41333333333333333,
                0.42,
                0.4266666666666667,
                0.43333333333333335,
                0.44,
                0.44666666666666666,
                0.4533333333333333,
                0.46,
                0.4666666666666667,
                0.47333333333333333,
                0.48,
                0.4866666666666667,
                0.49333333333333335,
                0.5,
                0.5066666666666667,
                0.5133333333333333,
                0.52,
                0.5266666666666666,
                0.5333333333333333,
                0.54,
                0.5466666666666666,
                0.5533333333333333,
                0.56,
                0.5666666666666667,
                0.5733333333333334,
                0.58,
                0.5866666666666667,
                0.5933333333333334,
                0.6,
                0.6066666666666667,
                0.6133333333333333,
                0.62,
                0.6266666666666667,
                0.6333333333333333,
                0.64,
                0.6466666666666666,
                0.6533333333333333,
                0.66,
                0.6666666666666666,
                0.6733333333333333,
                0.68,
                0.6866666666666666,
                0.6933333333333334,
                0.7,
                0.7066666666666667,
                0.7133333333333334,
                0.72,
                0.7266666666666667,
                0.7333333333333333,
                0.74,
                0.7466666666666667,
                0.7533333333333333,
                0.76,
                0.7666666666666667,
                0.7733333333333333,
                0.78,
                0.7866666666666666,
                0.7933333333333333,
                0.8,
                0.8066666666666666,
                0.8133333333333334,
                0.82,
                0.8266666666666667,
                0.8333333333333334,
                0.84,
                0.8466666666666667,
                0.8533333333333334,
                0.86,
                0.8666666666666667,
                0.8733333333333333,
                0.88,
                0.8866666666666667,
                0.8933333333333333,
                0.9,
                0.9066666666666666,
                0.9133333333333333,
                0.92,
                0.9266666666666666,
                0.9333333333333333,
                0.94,
                0.9466666666666667,
                0.9533333333333334,
                0.96,
                0.9666666666666667,
                0.9733333333333334,
                0.98,
                0.9866666666666667,
                0.9933333333333333,
                1,
                1.0066666666666666,
                1.0133333333333334,
                0,
                0.006666666666666667,
                0.013333333333333334,
                0.02,
                0.02666666666666667,
                0.03333333333333333,
                0.04,
                0.04666666666666667,
                0.05333333333333334,
                0.06,
                0.06666666666666667,
                0.07333333333333333,
                0.08,
                0.08666666666666667,
                0.09333333333333334,
                0.1,
                0.10666666666666667,
                0.11333333333333333,
                0.12,
                0.12666666666666668,
                0.13333333333333333,
                0.14,
                0.14666666666666667,
                0.15333333333333332,
                0.16,
                0.16666666666666666,
                0.17333333333333334,
                0.18,
                0.18666666666666668,
                0.19333333333333333,
                0.2,
                0.20666666666666667,
                0.21333333333333335,
                0.22,
                0.22666666666666666,
                0.23333333333333334,
                0.24,
                0.24666666666666667,
                0.25333333333333335,
                0.26,
                0.26666666666666666,
                0.2733333333333333,
                0.28,
                0.2866666666666667,
                0.29333333333333333,
                0.3,
                0.30666666666666664,
                0.31333333333333335,
                0.32,
                0.32666666666666666,
                0.3333333333333333,
                0.34,
                0.3466666666666667,
                0.35333333333333333,
                0.36,
                0.36666666666666664,
                0.37333333333333335,
                0.38,
                0.38666666666666666,
                0.3933333333333333,
                0.4,
                0.4066666666666667,
                0.41333333333333333,
                0.42,
                0.4266666666666667,
                0.43333333333333335,
                0.44,
                0.44666666666666666,
                0.4533333333333333,
                0.46,
                0.4666666666666667,
                0.47333333333333333,
                0.48,
                0.4866666666666667,
                0.49333333333333335,
                0.5,
                0.5066666666666667,
                0.5133333333333333,
                0.52,
                0.5266666666666666,
                0.5333333333333333,
                0.54,
                0.5466666666666666,
                0.5533333333333333,
                0.56,
                0.5666666666666667,
                0.5733333333333334,
                0.58,
                0.5866666666666667,
                0.5933333333333334,
                0.6,
                0.6066666666666667,
                0.6133333333333333,
                0.62,
                0.6266666666666667,
                0.6333333333333333,
                0.64,
                0.6466666666666666,
                0.6533333333333333,
                0.66,
                0.6666666666666666,
                0.6733333333333333,
                0.68,
                0.6866666666666666,
                0.6933333333333334,
                0.7,
                0.7066666666666667,
                0.7133333333333334,
                0.72,
                0.7266666666666667,
                0.7333333333333333,
                0.74,
                0.7466666666666667,
                0.7533333333333333,
                0.76,
                0.7666666666666667,
                0.7733333333333333,
                0.78,
                0.7866666666666666,
                0.7933333333333333,
                0.8,
                0.8066666666666666,
                0.8133333333333334,
                0.82,
                0.8266666666666667,
                0.8333333333333334,
                0.84,
                0.8466666666666667,
                0.8533333333333334,
                0.86,
                0.8666666666666667,
                0.8733333333333333,
                0.88,
                0.8866666666666667,
                0.8933333333333333,
                0.9,
                0.9066666666666666,
                0.9133333333333333,
                0.92,
                0.9266666666666666,
                0.9333333333333333,
                0.94,
                0.9466666666666667,
                0.9533333333333334,
                0.96,
                0.9666666666666667,
                0.9733333333333334,
                0.98,
                0.9866666666666667,
                0.9933333333333333,
                1,
                1.0066666666666666,
                1.0133333333333334
            ]
        },
        {
            "uuid": "d88ff61c-de8d-42c0-9275-57cd3fdbf1a0",
            "__class": "RunningController"
        },
        {
            "uuid": "31bc3ee1-a7f8-4aef-ae71-0691a77d24dc",
            "__class": "@egret/engine/TreeNode",
            "__extras": {
                "linkedID": "1"
            },
            "children": [
                {
                    "uuid": "e04d3d87-9b18-482f-9014-7a6d96df851d"
                },
                {
                    "uuid": "324aea1b-f277-461e-93a7-1f201000ae73"
                },
                {
                    "uuid": "02eff086-7cdd-4258-8ea6-1a7fc72ada8a"
                }
            ]
        },
        {
            "uuid": "e04d3d87-9b18-482f-9014-7a6d96df851d",
            "__class": "@egret/engine/TreeNode",
            "__extras": {
                "linkedID": "2"
            }
        },
        {
            "uuid": "7e945cc9-fe4d-4be8-a6ec-f27ee4681478",
            "__class": "@egret/engine/Transform",
            "__extras": {
                "linkedID": "d26862de-6b04-40de-a44c-d5515f82a285"
            }
        },
        {
            "uuid": "00b06e4f-24cf-4a1e-8921-682210f6976c",
            "__class": "@egret/render/MeshFilter",
            "__extras": {
                "linkedID": "7a96a582-44bb-4772-a818-abd1cf25fd89"
            }
        },
        {
            "uuid": "821f5179-9c36-4dfe-a2fc-083a6c2b6b76",
            "__class": "@egret/render/MeshRenderer",
            "__extras": {
                "linkedID": "a2e11ca3-9ba5-4a9a-bcd7-727f65924799"
            }
        },
        {
            "uuid": "324aea1b-f277-461e-93a7-1f201000ae73",
            "__class": "@egret/engine/TreeNode",
            "__extras": {
                "linkedID": "3"
            }
        },
        {
            "uuid": "81d9b71d-5839-49fa-a405-f9da45071a22",
            "__class": "@egret/engine/Transform",
            "__extras": {
                "linkedID": "adee2c93-e686-4df3-92cb-2ac72753c639"
            }
        },
        {
            "uuid": "c3ad720f-513b-4fb2-99ff-5adb42f226ed",
            "__class": "@egret/render/DirectionalLight",
            "__extras": {
                "linkedID": "a8c2a67a-d06d-48fe-b347-204006f66009"
            }
        },
        {
            "uuid": "f1525218-244c-4b84-8380-9d62f2596efd",
            "__class": "@egret/render/LightShadow",
            "__extras": {
                "linkedID": "35799c6e-cb80-4931-a033-9f35d8e0fa0c"
            }
        },
        {
            "uuid": "02eff086-7cdd-4258-8ea6-1a7fc72ada8a",
            "__class": "@egret/engine/TreeNode",
            "__extras": {
                "linkedID": "4"
            }
        },
        {
            "uuid": "03e266a3-4b48-41a6-a45d-32932704d2bc",
            "__class": "@egret/engine/Transform",
            "__extras": {
                "linkedID": "0d016c03-0d6c-451e-9a70-b13595c17ca6"
            }
        },
        {
            "uuid": "5e6abf76-85db-4009-b1d5-ebbff1da8043",
            "__class": "@egret/render/PointLight",
            "__extras": {
                "linkedID": "8b7fbce8-eb3b-420c-8a9c-c8ae8ccb0026"
            }
        },
        {
            "uuid": "755ff4ff-b2be-4b8d-9f2e-22078c11f173",
            "__class": "@egret/engine/Transform",
            "__extras": {
                "linkedID": "c311233f-eafb-4803-8b9d-ad3d621407ec"
            }
        },
        {
            "uuid": "0105e9c8-d226-4bf8-83c5-ceac80d1bb07",
            "__class": "@egret/engine/Scene"
        }
    ]
}